{
  "alternateadvancement_list": [
    {
      "ofxclassification": "Prestige",
      "name": "Prestige",
      "foreveryxpoints": 4,
      "ts": 1778773010.791981,
      "minimumpointsrequired": 0,
      "ofyclassification": "Prestige Expertise",
      "version": 2,
      "alternateadvancementnode_list": [
        {
          "pointsspentintreetounlock": 0,
          "ycoord": 4,
          "group": "",
          "description": "Umbral Barrier and Wards of the Eidolon have a chance to finish the reuse of Ancestral Channeling.",
          "classification": "Prestige",
          "title": "",
          "name": "Ancestral Assistance",
          "classificationpointsrequired": 0,
          "nodeid": 43749807,
          "minlevel": 1,
          "pointsspentgloballytounlock": 0,
          "spellcrc": 2110307444,
          "xcoord": 2,
          "titlelevel": 0,
          "icon": {
            "id": 683,
            "backdrop": 461
          },
          "pointspertier": 1,
          "maxtier": 2
        },
        {
          "pointsspentintreetounlock": 0,
          "ycoord": 4,
          "group": "",
          "description": "A replacement for Umbral Warding. Applies a powerful ward for a short duration on the mystic's group that prevents damage to them until the ward has absorbed its maximum amount of damage. This spell can be cast while moving, and cannot be interrupted.",
          "classification": "Prestige",
          "title": "",
          "name": "Umbral Barrier",
          "classificationpointsrequired": 0,
          "nodeid": 530489623,
          "minlevel": 1,
          "pointsspentgloballytounlock": 0,
          "spellcrc": 1624083660,
          "xcoord": 14,
          "titlelevel": 0,
          "icon": {
            "id": 71,
            "backdrop": 458
          },
          "pointspertier": 1,
          "maxtier": 1
        },
        {
          "pointsspentintreetounlock": 10,
          "ycoord": 11,
          "group": "",
          "description": "Monitors the damage that the group inflicts and then wards them for a small percentage of that damage. This spell can be cast while moving and through control effects.",
          "classification": "Prestige Mastery",
          "title": "",
          "name": "Ancestral Support",
          "classificationpointsrequired": 0,
          "nodeid": 546756002,
          "minlevel": 1,
          "pointsspentgloballytounlock": 0,
          "spellcrc": 126216784,
          "xcoord": 8,
          "titlelevel": 0,
          "icon": {
            "id": 363,
            "backdrop": 458
          },
          "pointspertier": 1,
          "maxtier": 3
        },
        {
          "pointsspentintreetounlock": 0,
          "ycoord": 14,
          "group": "",
          "description": "Grants the mystic additional damage following their attacks when they hit three increments of Ferocity of the Spirits. Cannot trigger more than once every 30 seconds.",
          "classification": "Spirit Beast",
          "title": "",
          "name": "Claws of the War Boar",
          "firstparentrequiredtier": 3,
          "firstparentid": 3114239000,
          "nodeid": 579675638,
          "minlevel": 1,
          "pointsspentgloballytounlock": 0,
          "spellcrc": 2992745703,
          "xcoord": 29,
          "titlelevel": 0,
          "icon": {
            "id": 618,
            "backdrop": 461
          },
          "pointspertier": 1,
          "classificationpointsrequired": 0,
          "maxtier": 3
        },
        {
          "pointsspentintreetounlock": 0,
          "ycoord": 1,
          "group": "",
          "description": "The mystic's temporary augmentations will apply an effect that triggers extra damage.",
          "classification": "Prestige",
          "title": "",
          "name": "Spiritblade",
          "classificationpointsrequired": 0,
          "nodeid": 831004251,
          "minlevel": 1,
          "pointsspentgloballytounlock": 0,
          "spellcrc": 553010730,
          "xcoord": 29,
          "titlelevel": 0,
          "icon": {
            "id": 223,
            "backdrop": 460
          },
          "pointspertier": 1,
          "maxtier": 3
        },
        {
          "pointsspentintreetounlock": 0,
          "ycoord": 17,
          "group": "",
          "description": "Immunization allows the target to cast while moving and makes them immune to knockbacks.",
          "classification": "Spirit Guide",
          "title": "the Spirit Guide",
          "name": "Spiritual Stability",
          "classificationpointsrequired": 6,
          "nodeid": 1269703992,
          "minlevel": 1,
          "pointsspentgloballytounlock": 0,
          "spellcrc": 1472643429,
          "xcoord": 8,
          "titlelevel": 1,
          "icon": {
            "id": 270,
            "backdrop": 460
          },
          "pointspertier": 1,
          "maxtier": 1
        },
        {
          "pointsspentintreetounlock": 0,
          "ycoord": 1,
          "group": "",
          "description": "The mystic has a chance to be able to cast while moving when they cast their primary wards.",
          "classification": "Prestige",
          "title": "",
          "name": "Enhanced Concentration",
          "classificationpointsrequired": 0,
          "nodeid": 1381367836,
          "minlevel": 1,
          "pointsspentgloballytounlock": 0,
          "spellcrc": 755314119,
          "xcoord": 14,
          "titlelevel": 0,
          "icon": {
            "id": 17,
            "backdrop": 461
          },
          "pointspertier": 1,
          "maxtier": 3
        },
        {
          "pointsspentintreetounlock": 0,
          "ycoord": 14,
          "group": "",
          "description": "Increases the weapon damage bonus of the group when the mystic enters Ferocity of Spirits with two spell increments. Cannot trigger more than once every 30 seconds.",
          "classification": "Spirit Beast",
          "title": "",
          "name": "Snow Rhino's Power",
          "firstparentrequiredtier": 3,
          "firstparentid": 3114239000,
          "nodeid": 1435112800,
          "minlevel": 1,
          "pointsspentgloballytounlock": 0,
          "spellcrc": 3311836273,
          "xcoord": 35,
          "titlelevel": 0,
          "icon": {
            "id": 470,
            "backdrop": 461
          },
          "pointspertier": 1,
          "classificationpointsrequired": 0,
          "maxtier": 3
        },
        {
          "pointsspentintreetounlock": 0,
          "ycoord": 4,
          "group": "",
          "description": "",
          "classification": "Prestige",
          "title": "",
          "name": "Spirits of Midnight",
          "classificationpointsrequired": 0,
          "nodeid": 1672491516,
          "minlevel": 1,
          "pointsspentgloballytounlock": 0,
          "spellcrc": 1926130061,
          "xcoord": 41,
          "titlelevel": 0,
          "icon": {
            "id": 343,
            "backdrop": 461
          },
          "pointspertier": 1,
          "maxtier": 2
        },
        {
          "pointsspentintreetounlock": 0,
          "ycoord": 14,
          "group": "",
          "description": "Ancestral Support will heal the target when it triggers.",
          "classification": "Spirit Guide",
          "title": "",
          "name": "Helpful Spirits",
          "firstparentrequiredtier": 3,
          "firstparentid": 546756002,
          "nodeid": 2067395976,
          "minlevel": 1,
          "pointsspentgloballytounlock": 0,
          "spellcrc": 682456455,
          "xcoord": 14,
          "titlelevel": 0,
          "icon": {
            "id": 211,
            "backdrop": 458
          },
          "pointspertier": 1,
          "classificationpointsrequired": 0,
          "maxtier": 3
        },
        {
          "pointsspentintreetounlock": 10,
          "ycoord": 11,
          "group": "",
          "description": "Ritual of Alacrity will gain triggered effects that ward when casting heals and inflict damage when attacking.",
          "classification": "Prestige Mastery",
          "title": "",
          "name": "Mystic Ritual",
          "classificationpointsrequired": 0,
          "nodeid": 2411094965,
          "minlevel": 1,
          "pointsspentgloballytounlock": 0,
          "spellcrc": 526052004,
          "xcoord": 22,
          "titlelevel": 0,
          "icon": {
            "id": 619,
            "backdrop": 460
          },
          "pointspertier": 1,
          "maxtier": 3
        },
        {
          "pointsspentintreetounlock": 0,
          "ycoord": 1,
          "group": "",
          "description": "The priest's heals have a chance to increase the target's flurry chance and doublecast chance.",
          "classification": "Prestige",
          "title": "",
          "name": "Invigorate",
          "classificationpointsrequired": 0,
          "nodeid": 2459813165,
          "minlevel": 1,
          "pointsspentgloballytounlock": 0,
          "spellcrc": 2212732252,
          "xcoord": 2,
          "titlelevel": 0,
          "icon": {
            "id": 733,
            "backdrop": 460
          },
          "pointspertier": 1,
          "maxtier": 3
        },
        {
          "pointsspentintreetounlock": 0,
          "ycoord": 14,
          "group": "",
          "description": "Ancestral Support will make the group immune to certain control effects.",
          "classification": "Spirit Guide",
          "title": "",
          "name": "Whispers of the Past",
          "firstparentrequiredtier": 3,
          "firstparentid": 546756002,
          "nodeid": 2625755279,
          "minlevel": 1,
          "pointsspentgloballytounlock": 0,
          "spellcrc": 3474282624,
          "xcoord": 8,
          "titlelevel": 0,
          "icon": {
            "id": 225,
            "backdrop": 458
          },
          "pointspertier": 1,
          "classificationpointsrequired": 0,
          "maxtier": 3
        },
        {
          "pointsspentintreetounlock": 0,
          "ycoord": 4,
          "group": "",
          "description": "Enhances Bolster to improve movement speed and Crit Bonus. Additionally, Bolster shapeshifts the target into a werewolf and grants a lifetap on attacks.",
          "classification": "Prestige",
          "title": "",
          "name": "Full Moon",
          "classificationpointsrequired": 0,
          "nodeid": 2786529138,
          "minlevel": 1,
          "pointsspentgloballytounlock": 0,
          "spellcrc": 3077134083,
          "xcoord": 29,
          "titlelevel": 0,
          "icon": {
            "id": 375,
            "backdrop": 460
          },
          "pointspertier": 1,
          "maxtier": 1
        },
        {
          "pointsspentintreetounlock": 0,
          "ycoord": 14,
          "group": "",
          "description": "",
          "classification": "Spirit Beast",
          "title": "",
          "name": "White Wolf's Howl",
          "firstparentrequiredtier": 3,
          "firstparentid": 3114239000,
          "nodeid": 2989635687,
          "minlevel": 1,
          "pointsspentgloballytounlock": 0,
          "spellcrc": 585019766,
          "xcoord": 41,
          "titlelevel": 0,
          "icon": {
            "id": 188,
            "backdrop": 461
          },
          "pointspertier": 1,
          "classificationpointsrequired": 0,
          "maxtier": 3
        },
        {
          "pointsspentintreetounlock": 10,
          "ycoord": 11,
          "group": "",
          "description": "Grants the mystic a chance to gain an incremental Crit Bonus augmentation. This ability increments to 3 and does not refresh the duration once at rank 3.",
          "classification": "Prestige Mastery",
          "title": "",
          "name": "Ferocity of Spirits",
          "classificationpointsrequired": 0,
          "nodeid": 3114239000,
          "minlevel": 1,
          "pointsspentgloballytounlock": 0,
          "spellcrc": 2660023274,
          "xcoord": 35,
          "titlelevel": 0,
          "icon": {
            "id": 585,
            "backdrop": 461
          },
          "pointspertier": 1,
          "maxtier": 3
        },
        {
          "pointsspentintreetounlock": 0,
          "ycoord": 7,
          "group": "",
          "description": "Grant's Crit Bonus Overcap to the Mystic.",
          "classification": "Prestige Expertise",
          "title": "",
          "name": "Multi-Attack Mastery",
          "classificationpointsrequired": 0,
          "nodeid": 3318168136,
          "minlevel": 1,
          "pointsspentgloballytounlock": 0,
          "spellcrc": 3568919097,
          "xcoord": 35,
          "titlelevel": 0,
          "icon": {
            "id": 224,
            "backdrop": 461
          },
          "pointspertier": 1,
          "maxtier": 1
        },
        {
          "pointsspentintreetounlock": 0,
          "ycoord": 7,
          "group": "",
          "description": "Grant's Fervor to the Mystic.",
          "classification": "Prestige Expertise",
          "title": "",
          "name": "Potent Medium",
          "classificationpointsrequired": 0,
          "nodeid": 3385278986,
          "minlevel": 1,
          "pointsspentgloballytounlock": 0,
          "spellcrc": 3063181265,
          "xcoord": 8,
          "titlelevel": 0,
          "icon": {
            "id": 206,
            "backdrop": 461
          },
          "pointspertier": 1,
          "maxtier": 1
        },
        {
          "pointsspentintreetounlock": 20,
          "ycoord": 17,
          "group": "",
          "description": "Makes Ancestral Avatar apply to the group.",
          "classification": "Prestige Mastery",
          "title": "",
          "name": "Spiritual Medium",
          "classificationpointsrequired": 0,
          "nodeid": 3424756157,
          "minlevel": 1,
          "pointsspentgloballytounlock": 0,
          "spellcrc": 3366231788,
          "xcoord": 22,
          "titlelevel": 0,
          "icon": {
            "id": 387,
            "backdrop": 458
          },
          "pointspertier": 2,
          "maxtier": 1
        },
        {
          "pointsspentintreetounlock": 0,
          "ycoord": 14,
          "group": "",
          "description": "Ancestral Support will gain a chance to inflict magic damage to enemies.",
          "classification": "Spirit Guide",
          "title": "",
          "name": "Past's Vengeance",
          "firstparentrequiredtier": 3,
          "firstparentid": 546756002,
          "nodeid": 3951487001,
          "minlevel": 1,
          "pointsspentgloballytounlock": 0,
          "spellcrc": 3088214038,
          "xcoord": 2,
          "titlelevel": 0,
          "icon": {
            "id": 267,
            "backdrop": 458
          },
          "pointspertier": 1,
          "classificationpointsrequired": 0,
          "maxtier": 3
        },
        {
          "pointsspentintreetounlock": 0,
          "ycoord": 17,
          "group": "",
          "description": "Wards the target based on the number of increments of Ferocity of Spirits. This spell can be cast while casting other spells.",
          "classification": "Spirit Beast",
          "title": "the Spirit Beast",
          "name": "Barrier of the Spirits",
          "classificationpointsrequired": 6,
          "nodeid": 4098263755,
          "minlevel": 1,
          "pointsspentgloballytounlock": 0,
          "spellcrc": 3783315302,
          "xcoord": 35,
          "titlelevel": 1,
          "icon": {
            "id": 502,
            "backdrop": 460
          },
          "pointspertier": 1,
          "maxtier": 1
        },
        {
          "pointsspentintreetounlock": 0,
          "ycoord": 1,
          "group": "",
          "description": "The priest's hostile actions have a chance to trigger damage reduction for their group.",
          "classification": "Prestige",
          "title": "",
          "name": "Brainstorm",
          "classificationpointsrequired": 0,
          "nodeid": 4220322430,
          "minlevel": 1,
          "pointsspentgloballytounlock": 0,
          "spellcrc": 2229153701,
          "xcoord": 41,
          "titlelevel": 0,
          "icon": {
            "id": 50,
            "backdrop": 458
          },
          "pointspertier": 1,
          "maxtier": 3
        }
      ],
      "maxpointsperlevelnode_list": [
        {
          "maxpoints": 25,
          "level": 90
        }
      ],
      "iswardertree": "false",
      "last_update": 1778773010.791981,
      "maximumpoints": 0,
      "unlocksypoints": 1,
      "id": 100
    }
  ],
  "returned": 1,
  "limit": 1,
  "min_ts": 1778773010.791981,
  "max_ts": 1778773010.791981
}